m3u8_video_downloader
